README.md
setup.py
date_super_utils/__init__.py
date_super_utils/main.py
date_super_utils.egg-info/PKG-INFO
date_super_utils.egg-info/SOURCES.txt
date_super_utils.egg-info/dependency_links.txt
date_super_utils.egg-info/requires.txt
date_super_utils.egg-info/top_level.txt