Metadata-Version: 2.1
Name: date-super-utils
Version: 0.0.4
Summary: Date utils
Author: Vladyslav Zadorozhnyi
Author-email: zadorozhnyi.devback@gmail.com
License: MIT
